{
  "hints": [],
  "groups": [
    {
      "sourceType": "tacos.DruidConfig",
      "name": "spring.datasource",
      "sourceMethod": "druidDataSource()",
      "type": "javax.sql.DataSource"
    },
    {
      "sourceType": "tacos.DiscountCodeProps",
      "name": "taco.discount",
      "type": "tacos.DiscountCodeProps"
    },
    {
      "sourceType": "tacos.web.OrderProps",
      "name": "taco.orders",
      "type": "tacos.web.OrderProps"
    }
  ],
  "properties": [
    {
      "sourceType": "tacos.DiscountCodeProps",
      "name": "taco.discount.codes",
      "type": "java.util.Map<java.lang.String,java.lang.Integer>"
    },
    {
      "sourceType": "tacos.web.OrderProps",
      "defaultValue": 20,
      "name": "taco.orders.page-size",
      "type": "java.lang.Integer"
    },
    {
      "name": "taco.orders.pageSize",
      "description": "sets the maximum number of orders to display in a list.",
      "type": "java.lang.String"
    }
  ]
}